fchapuis_calculator_package/__init__.py
fchapuis_calculator_package/setup.py
fchapuis_calculator_package/calculator_pckg/__init__.py
fchapuis_calculator_package/calculator_pckg/calculator.py
fchapuis_calculator_package/tests/__init__.py
fchapuis_calculator_package/tests/requirements.txt
fchapuis_calculator_package/tests/test_calculator.py
fchapuis_calculator_package-0.1.0.dist-info/LICENSE
fchapuis_calculator_package-0.1.0.dist-info/WHEEL
fchapuis_calculator_package-0.1.0.dist-info/METADATA
fchapuis_calculator_package-0.1.0.dist-info/RECORD
